file_finder/cli.py
file_finder/constants.py
file_finder/exceptions.py
file_finder/finder.py
file_finder/utils.py
phynder-0.1.1.dist-info/METADATA
phynder-0.1.1.dist-info/WHEEL
phynder-0.1.1.dist-info/entry_points.txt
phynder-0.1.1.dist-info/RECORD
